LICENSE.txt
MANIFEST.in
README.rst
development.txt
requirements.txt
setup.py
docs/amqp-xml-doc0-9-1.pdf
docs/amqp0-9-1.pdf
docs/rabbitmq.amqp0-9-1.xml
haigha/__init__.py
haigha/channel.py
haigha/channel_pool.py
haigha/connection.py
haigha/exceptions.py
haigha/message.py
haigha/reader.py
haigha/writer.py
haigha.egg-info/PKG-INFO
haigha.egg-info/SOURCES.txt
haigha.egg-info/dependency_links.txt
haigha.egg-info/pbr.json
haigha.egg-info/top_level.txt
haigha/classes/__init__.py
haigha/classes/basic_class.py
haigha/classes/channel_class.py
haigha/classes/exchange_class.py
haigha/classes/protocol_class.py
haigha/classes/queue_class.py
haigha/classes/transaction_class.py
haigha/connections/__init__.py
haigha/connections/rabbit_connection.py
haigha/frames/__init__.py
haigha/frames/content_frame.py
haigha/frames/frame.py
haigha/frames/header_frame.py
haigha/frames/heartbeat_frame.py
haigha/frames/method_frame.py
haigha/transports/__init__.py
haigha/transports/event_transport.py
haigha/transports/gevent_transport.py
haigha/transports/socket_transport.py
haigha/transports/transport.py
scripts/console
scripts/rabbit_table_test
scripts/stress_test
scripts/test
scripts/regression/issue_24
scripts/regression/issue_31
scripts/regression/issue_33