Metadata-Version: 1.1
Name: haigha
Version: 0.9.0
Summary: Synchronous and asynchronous AMQP client library
Home-page: https://github.com/agoragames/haigha
Author: Vitaly Babiy, Aaron Westendorf
Author-email: vbabiy@agoragames.com, aaron@agoragames.com
License: LICENSE.txt
Keywords: python,amqp,event,rabbitmq
Platform: UNKNOWN
Classifier: Development Status :: 5 - Production/Stable
Classifier: License :: OSI Approved :: BSD License
Classifier: Intended Audience :: Developers
Classifier: Operating System :: POSIX
Classifier: Topic :: Communications
Classifier: Topic :: System :: Distributed Computing
Classifier: Topic :: Software Development :: Libraries :: Python Modules
Classifier: Programming Language :: Python
Classifier: Programming Language :: Python :: 2.7
Classifier: Topic :: Software Development :: Libraries
